nengo_ocl/__init__.py
nengo_ocl/ast_conversion.py
nengo_ocl/builder.py
nengo_ocl/clra_gemv.py
nengo_ocl/clra_nonlinearities.py
nengo_ocl/clraggedarray.py
nengo_ocl/operators.py
nengo_ocl/plan.py
nengo_ocl/planners.py
nengo_ocl/raggedarray.py
nengo_ocl/simulator.py
nengo_ocl/utils.py
nengo_ocl/version.py
nengo_ocl/tests/__init__.py
nengo_ocl/tests/test_ast_conversion.py
nengo_ocl/tests/test_clra_gemv.py
nengo_ocl/tests/test_clra_nonlinearities.py
nengo_ocl/tests/test_clraggedarray.py
nengo_ocl/tests/test_nengo_tests.py
nengo_ocl/tests/test_operators.py
nengo_ocl/tests/test_planners.py
nengo_ocl/tests/test_simulator.py
nengo_ocl-3.0.0.dist-info/LICENSE.rst
nengo_ocl-3.0.0.dist-info/METADATA
nengo_ocl-3.0.0.dist-info/WHEEL
nengo_ocl-3.0.0.dist-info/entry_points.txt
nengo_ocl-3.0.0.dist-info/top_level.txt
nengo_ocl-3.0.0.dist-info/RECORD
