Metadata-Version: 2.1
Name: nengo-ocl
Version: 3.0.0
Summary: OpenCL-based simulator for Nengo neural models
Home-page: https://www.nengo.ai/nengo-ocl/
Author: Applied Brain Research
Author-email: info@appliedbrainresearch.com
License: GNU General Public License, version 2
Classifier: Development Status :: 4 - Beta
Classifier: Framework :: Nengo
Classifier: Intended Audience :: Science/Research
Classifier: License :: OSI Approved :: GNU General Public License v2 (GPLv2)
Classifier: Operating System :: OS Independent
Classifier: Programming Language :: Python
Classifier: Programming Language :: Python :: 3.6
Classifier: Programming Language :: Python :: 3.7
Classifier: Topic :: Scientific/Engineering
Classifier: Topic :: Scientific/Engineering :: Artificial Intelligence
Requires-Python: >=3.8
License-File: LICENSE.rst
Requires-Dist: nengo (>=3.1.0)
Requires-Dist: mako
Requires-Dist: pyopencl
Provides-Extra: all
Requires-Dist: click (>=7.0) ; extra == 'all'
Requires-Dist: matplotlib (>=1.4) ; extra == 'all'
Requires-Dist: nbsphinx ; extra == 'all'
Requires-Dist: nengo-sphinx-theme (>=1.2.0) ; extra == 'all'
Requires-Dist: numpydoc (>=0.6.0) ; extra == 'all'
Requires-Dist: sphinx (>=1.8) ; extra == 'all'
Requires-Dist: pytest (>=3.6.0) ; extra == 'all'
Requires-Dist: pytest-allclose (>=1.0.0) ; extra == 'all'
Requires-Dist: pytest-plt (>=1.0.0) ; extra == 'all'
Requires-Dist: pytest-rng (>=1.0.0) ; extra == 'all'
Provides-Extra: docs
Requires-Dist: click (>=7.0) ; extra == 'docs'
Requires-Dist: matplotlib (>=1.4) ; extra == 'docs'
Requires-Dist: nbsphinx ; extra == 'docs'
Requires-Dist: nengo-sphinx-theme (>=1.2.0) ; extra == 'docs'
Requires-Dist: numpydoc (>=0.6.0) ; extra == 'docs'
Requires-Dist: sphinx (>=1.8) ; extra == 'docs'
Provides-Extra: optional
Provides-Extra: tests
Requires-Dist: matplotlib (>=1.4) ; extra == 'tests'
Requires-Dist: pytest (>=3.6.0) ; extra == 'tests'
Requires-Dist: pytest-allclose (>=1.0.0) ; extra == 'tests'
Requires-Dist: pytest-plt (>=1.0.0) ; extra == 'tests'
Requires-Dist: pytest-rng (>=1.0.0) ; extra == 'tests'
